per_segment_anything/__init__.py
per_segment_anything/automatic_mask_generator.py
per_segment_anything/build_sam.py
per_segment_anything/predictor.py
per_segment_anything/modeling/__init__.py
per_segment_anything/modeling/common.py
per_segment_anything/modeling/image_encoder.py
per_segment_anything/modeling/mask_decoder.py
per_segment_anything/modeling/prompt_encoder.py
per_segment_anything/modeling/sam.py
per_segment_anything/modeling/transformer.py
per_segment_anything/utils/__init__.py
per_segment_anything/utils/amg.py
per_segment_anything/utils/onnx.py
per_segment_anything/utils/transforms.py
personalize_sam-1.0.3.dist-info/LICENSE.txt
personalize_sam-1.0.3.dist-info/METADATA
personalize_sam-1.0.3.dist-info/WHEEL
personalize_sam-1.0.3.dist-info/dependency_links.txt
personalize_sam-1.0.3.dist-info/top_level.txt
personalize_sam-1.0.3.dist-info/RECORD
