Metadata-Version: 2.1
Name: personalize-sam
Version: 1.0.3
Summary: Personalize-SAM package
Home-page: https://github.com/ZrrSkywalker/Personalize-SAM
Project-URL: Homepage, https://github.com/ZrrSkywalker/Personalize-SAM
Classifier: License :: OSI Approved :: MIT License
Classifier: Programming Language :: Python
Classifier: Programming Language :: Python :: 3
Requires-Python: >=3.8
License-File: LICENSE.txt
Provides-Extra: dev
Requires-Dist: black ; extra == 'dev'
Requires-Dist: pytest ; extra == 'dev'
